gps2topo_poi/__init__.py
gps2topo_poi/dwell_time_stop_classifier_poi_extraction.py
gps2topo_poi/running_time_poi_extraction.py
gps2topo_poi/topological_feature_extraction.py
gps2topo_poi-0.1.3.dist-info/LICENSE
gps2topo_poi-0.1.3.dist-info/METADATA
gps2topo_poi-0.1.3.dist-info/WHEEL
gps2topo_poi-0.1.3.dist-info/top_level.txt
gps2topo_poi-0.1.3.dist-info/RECORD
