Metadata-Version: 2.1
Name: gps2topo_poi
Version: 0.1.3
Summary: A Python package to use GPS data of public transit routes and append topographical and Points of Interests (POI) related features.
Home-page: https://github.com/kavindu-w/Explainable-Bus-Arrival-Time-Prediction-Model-with-Improved-Features-Related-to-Topography-and-POIs
Author: kavindu-w
Author-email: akwarnakulasuriya@gmail.com
License: MIT
Project-URL: Homepage, https://github.com/kavindu-w/Explainable-Bus-Arrival-Time-Prediction-Model-with-Improved-Features-Related-to-Topography-and-POIs
Project-URL: Source, https://github.com/kavindu-w/Explainable-Bus-Arrival-Time-Prediction-Model-with-Improved-Features-Related-to-Topography-and-POIs/tree/main/src/code/Feature_Extraction/gps2topo_poi
Project-URL: Download, https://pypi.org/project/gps2topo-poi/
Keywords: Topolographical data,Elevation,Points of Interest,POI,GPS,Travel Time,Public Transit,Heterogeneous Traffic Conditions
Classifier: Development Status :: 3 - Alpha
Classifier: Intended Audience :: Developers
Classifier: Intended Audience :: Science/Research
Classifier: Programming Language :: Python :: 3 :: Only
Classifier: Programming Language :: Python :: 3.6
Classifier: Programming Language :: Python :: 3.7
Classifier: Programming Language :: Python :: 3.8
Classifier: Programming Language :: Python :: 3.9
Classifier: Programming Language :: Python :: 3.10
Classifier: Programming Language :: Python :: 3.11
Classifier: License :: OSI Approved :: MIT License
Classifier: Operating System :: OS Independent
Classifier: Topic :: Scientific/Engineering
Classifier: Topic :: Software Development
Requires-Python: >=3.6
License-File: LICENSE
Requires-Dist: pandas
Requires-Dist: numpy
Requires-Dist: osmnx
Requires-Dist: tqdm
